{
  "development": {
      "CONTEXT_URI" : "http://app.qdbitbucket:4000",
      "QD_REST_APP_URL" : "http://localhost:7000",
      "SESSION_SECRET" : "bitbucketQdTest",
      "BITBUCKET_CONSUMER_KEY" : "qV9nLJEV3qdaazVXdZ",
      "BITBUCKET_CONSUMER_SECRET" : "Z3Am42b7eTP6rCnVTxNmNm55pURqCCT3",
      "MONGO_URI" : "mongodb://localhost/qd_bitbucket_app"
  },
  "test": {
      "CONTEXT_URI" : "http://app.qdbitbucket:4000",
      "QD_REST_APP_URL" : "http://localhost:7000",
      "SESSION_SECRET" : "bitbucketQdTest",
      "BITBUCKET_CONSUMER_KEY" : "qV9nLJEV3qdaazVXdZ",
      "BITBUCKET_CONSUMER_SECRET" : "Z3Am42b7eTP6rCnVTxNmNm55pURqCCT3",
      "MONGO_URI" : "mongodb://localhost/qd_bitbucket_app_test"
  },
  "production": {
      "CONTEXT_URI" : "http://app.qdbitbucket:4000",
      "QD_REST_APP_URL" : "http://localhost:7000",
      "SESSION_SECRET" : "bitbucketQdTest",
      "BITBUCKET_CONSUMER_KEY" : "qV9nLJEV3qdaazVXdZ",
      "BITBUCKET_CONSUMER_SECRET" : "Z3Am42b7eTP6rCnVTxNmNm55pURqCCT3",
      "MONGO_URI" : "mongodb://localhost/qd_bitbucket_app_test"
  }
}
